eepyc.py
eepyc-0.3.0.dist-info/LICENSE.md
eepyc-0.3.0.dist-info/METADATA
eepyc-0.3.0.dist-info/WHEEL
eepyc-0.3.0.dist-info/entry_points.txt
eepyc-0.3.0.dist-info/top_level.txt
eepyc-0.3.0.dist-info/RECORD
