Metadata-Version: 2.1
Name: eepyc
Version: 0.3.0
Summary: Evaluate embedded Python code in textual data
Home-page: https://github.com/justinyaodu/eepyc
Author: Justin Yao Du
Author-email: justinyaodu@gmail.com
License: UNKNOWN
Platform: UNKNOWN
Classifier: Development Status :: 3 - Alpha
Classifier: Programming Language :: Python :: 3
Classifier: License :: OSI Approved :: MIT License
Classifier: Operating System :: OS Independent
Classifier: Environment :: Console
Classifier: Topic :: Text Processing :: Filters
Requires-Python: >=3.6
